scrcpy_client_def/__init__.py
scrcpy_client_def/utils.py
scrcpy_client_def/defs/__init__.py
scrcpy_client_def/defs/android_def.py
scrcpy_client_def/defs/control_msg.py
scrcpy_client_def/defs/device_msg.py
scrcpy_client_def/defs/hid_def.py
scrcpy_client_def/defs/mouse_button.py
scrcpy_client_def/defs/sdl_def.py
scrcpy_client_def/events/__init__.py
scrcpy_client_def/events/clipboard_event.py
scrcpy_client_def/events/hid_event.py
scrcpy_client_def/events/inject_event.py
scrcpy_client_def-0.1.15.dist-info/METADATA
scrcpy_client_def-0.1.15.dist-info/WHEEL
scrcpy_client_def-0.1.15.dist-info/top_level.txt
scrcpy_client_def-0.1.15.dist-info/RECORD
