Metadata-Version: 2.4
Name: scrcpy_client_def
Version: 0.1.15
Summary: A partial implementation of scrcpy.
Author-email: BHznJNs <bhznjns@qq.com>
License-Expression: Apache-2.0
Project-URL: Homepage, https://github.com/BHznJNs/scrcpy_client
Project-URL: Issues, https://github.com/BHznJNs/scrcpy_client/issues
Classifier: Programming Language :: Python :: 3
Classifier: Operating System :: OS Independent
Requires-Python: >=3.9
